crow_client/__init__.py
crow_client/clients/__init__.py
crow_client/clients/job_client.py
crow_client/clients/rest_client.py
crow_client/models/__init__.py
crow_client/models/app.py
crow_client/models/client.py
crow_client/models/rest.py
crow_client/utils/__init__.py
crow_client/utils/module_utils.py
crow_client-0.3.14.dist-info/METADATA
crow_client-0.3.14.dist-info/WHEEL
crow_client-0.3.14.dist-info/top_level.txt
crow_client-0.3.14.dist-info/RECORD
