Metadata-Version: 2.4
Name: crow-client
Version: 0.3.14
Summary: A client for interacting with endpoints of the FutureHouse crow service.
Author-email: FutureHouse technical staff <hello@futurehouse.org>
Classifier: Operating System :: OS Independent
Classifier: Programming Language :: Python :: 3 :: Only
Classifier: Programming Language :: Python :: 3.11
Classifier: Programming Language :: Python :: 3.12
Classifier: Programming Language :: Python
Requires-Python: <3.13,>=3.11
Requires-Dist: cloudpickle
Requires-Dist: dm-tree<0.1.9
Requires-Dist: fhaviary
Requires-Dist: httpx
Requires-Dist: ldp>=0.22.0
Requires-Dist: pydantic
Requires-Dist: python-dotenv
Requires-Dist: tenacity
Provides-Extra: dev
Requires-Dist: black; extra == "dev"
Requires-Dist: jupyter; extra == "dev"
Requires-Dist: jupyterlab; extra == "dev"
Requires-Dist: mypy; extra == "dev"
Requires-Dist: notebook; extra == "dev"
Requires-Dist: pre-commit; extra == "dev"
Requires-Dist: pylint; extra == "dev"
Requires-Dist: pylint-per-file-ignores; extra == "dev"
Requires-Dist: pylint-pydantic; extra == "dev"
Requires-Dist: pytest; extra == "dev"
Requires-Dist: pytest-rerunfailures; extra == "dev"
Requires-Dist: pytest-subtests; extra == "dev"
Requires-Dist: pytest-timeout; extra == "dev"
Requires-Dist: pytest-xdist; extra == "dev"
Requires-Dist: ruff; extra == "dev"
Requires-Dist: setuptools_scm; extra == "dev"
